{
    "last_updated": "2026-07-03 12:38:35",
    "2330.TW": {
        "price": 2445.0,
        "change": -0.811359,
        "book_value": 227.166,
        "pe": 33.175034,
        "eps": 73.7,
        "est_revenue": "預估中",
        "est_eps": "預估中",
        "est_dividend": "預估中",
        "margin_ratio_10d": 15.2,
        "institutional_data": [
            {
                "法人": "外資",
                "買賣超(張)": 1500
            },
            {
                "法人": "投信",
                "買賣超(張)": 300
            },
            {
                "法人": "自營商",
                "買賣超(張)": -120
            }
        ],
        "broker_data": [
            {
                "券商名稱": "凱基-台北",
                "買賣超(張)": 450
            },
            {
                "券商名稱": "富邦-建國",
                "買賣超(張)": -120
            },
            {
                "券商名稱": "元大-總公司",
                "買賣超(張)": 300
            }
        ],
        "ai_prediction": "綜合指標：趨勢穩健。",
        "news_analysis": "近期成交量穩定，外資持股比例上升。"
    },
    "2317.TW": {
        "price": 240.5,
        "change": 0.6276151,
        "book_value": 126.905,
        "pe": 17.934378,
        "eps": 13.41,
        "est_revenue": "預估中",
        "est_eps": "預估中",
        "est_dividend": "預估中",
        "margin_ratio_10d": 15.2,
        "institutional_data": [
            {
                "法人": "外資",
                "買賣超(張)": 1500
            },
            {
                "法人": "投信",
                "買賣超(張)": 300
            },
            {
                "法人": "自營商",
                "買賣超(張)": -120
            }
        ],
        "broker_data": [
            {
                "券商名稱": "凱基-台北",
                "買賣超(張)": 450
            },
            {
                "券商名稱": "富邦-建國",
                "買賣超(張)": -120
            },
            {
                "券商名稱": "元大-總公司",
                "買賣超(張)": 300
            }
        ],
        "ai_prediction": "綜合指標：趨勢穩健。",
        "news_analysis": "近期成交量穩定，外資持股比例上升。"
    },
    "2454.TW": {
        "price": 4195.0,
        "change": -3.452244,
        "book_value": 244.52,
        "pe": 63.522106,
        "eps": 66.04,
        "est_revenue": "預估中",
        "est_eps": "預估中",
        "est_dividend": "預估中",
        "margin_ratio_10d": 15.2,
        "institutional_data": [
            {
                "法人": "外資",
                "買賣超(張)": 1500
            },
            {
                "法人": "投信",
                "買賣超(張)": 300
            },
            {
                "法人": "自營商",
                "買賣超(張)": -120
            }
        ],
        "broker_data": [
            {
                "券商名稱": "凱基-台北",
                "買賣超(張)": 450
            },
            {
                "券商名稱": "富邦-建國",
                "買賣超(張)": -120
            },
            {
                "券商名稱": "元大-總公司",
                "買賣超(張)": 300
            }
        ],
        "ai_prediction": "綜合指標：趨勢穩健。",
        "news_analysis": "近期成交量穩定，外資持股比例上升。"
    },
    "1301.TW": {
        "price": 62.1,
        "change": 4.020097,
        "book_value": 61.299,
        "pe": 0.0,
        "eps": -1.08,
        "est_revenue": "預估中",
        "est_eps": "預估中",
        "est_dividend": "預估中",
        "margin_ratio_10d": 15.2,
        "institutional_data": [
            {
                "法人": "外資",
                "買賣超(張)": 1500
            },
            {
                "法人": "投信",
                "買賣超(張)": 300
            },
            {
                "法人": "自營商",
                "買賣超(張)": -120
            }
        ],
        "broker_data": [
            {
                "券商名稱": "凱基-台北",
                "買賣超(張)": 450
            },
            {
                "券商名稱": "富邦-建國",
                "買賣超(張)": -120
            },
            {
                "券商名稱": "元大-總公司",
                "買賣超(張)": 300
            }
        ],
        "ai_prediction": "綜合指標：趨勢穩健。",
        "news_analysis": "近期成交量穩定，外資持股比例上升。"
    },
    "2303.TW": {
        "price": 170.5,
        "change": 3.021148,
        "book_value": 32.332,
        "pe": 43.274113,
        "eps": 3.94,
        "est_revenue": "預估中",
        "est_eps": "預估中",
        "est_dividend": "預估中",
        "margin_ratio_10d": 15.2,
        "institutional_data": [
            {
                "法人": "外資",
                "買賣超(張)": 1500
            },
            {
                "法人": "投信",
                "買賣超(張)": 300
            },
            {
                "法人": "自營商",
                "買賣超(張)": -120
            }
        ],
        "broker_data": [
            {
                "券商名稱": "凱基-台北",
                "買賣超(張)": 450
            },
            {
                "券商名稱": "富邦-建國",
                "買賣超(張)": -120
            },
            {
                "券商名稱": "元大-總公司",
                "買賣超(張)": 300
            }
        ],
        "ai_prediction": "綜合指標：趨勢穩健。",
        "news_analysis": "近期成交量穩定，外資持股比例上升。"
    },
    "2308.TW": {
        "price": 2075.0,
        "change": 5.3299494,
        "book_value": 115.318,
        "pe": 90.0217,
        "eps": 23.05,
        "est_revenue": "預估中",
        "est_eps": "預估中",
        "est_dividend": "預估中",
        "margin_ratio_10d": 15.2,
        "institutional_data": [
            {
                "法人": "外資",
                "買賣超(張)": 1500
            },
            {
                "法人": "投信",
                "買賣超(張)": 300
            },
            {
                "法人": "自營商",
                "買賣超(張)": -120
            }
        ],
        "broker_data": [
            {
                "券商名稱": "凱基-台北",
                "買賣超(張)": 450
            },
            {
                "券商名稱": "富邦-建國",
                "買賣超(張)": -120
            },
            {
                "券商名稱": "元大-總公司",
                "買賣超(張)": 300
            }
        ],
        "ai_prediction": "綜合指標：趨勢穩健。",
        "news_analysis": "近期成交量穩定，外資持股比例上升。"
    }
}